<?xml version="1.0" encoding="UTF-8"?>
<GenRun Id="impl_1" LaunchPart="xc7a100tcsg324-1" LaunchTime="1774537051">
  <File Type="OPT-DCP" Name="AHBliteTop_opt.dcp"/>
  <File Type="RUN-CONSTRS" Name="$PDATADIR/runs/impl_1/constrs_in.xml"/>
  <File Type="RUN-SRCS" Name="$PDATADIR/runs/impl_1/sources.xml"/>
  <File Type="PWROPT-DCP" Name="AHBliteTop_pwropt.dcp"/>
  <File Type="ROUTE-DCP" Name="AHBliteTop_routed.dcp"/>
  <File Type="PA-TCL" Name="AHBliteTop.tcl"/>
  <File Type="RUN-STRAT" Name="$PDATADIR/runs/impl_1/impl_1.psg"/>
  <File Type="OPT-DRC" Name="AHBliteTop_drc_opted.rpt"/>
  <File Type="PWROPT-DRC" Name="AHBliteTop_drc_pwropted.rpt"/>
  <File Type="OPT-HWDEF" Name="AHBliteTop.hwdef"/>
  <File Type="PLACE-DCP" Name="AHBliteTop_placed.dcp"/>
  <File Type="PLACE-IO" Name="AHBliteTop_io_placed.rpt"/>
  <File Type="PLACE-CLK" Name="AHBliteTop_clock_utilization_placed.rpt"/>
  <File Type="PLACE-UTIL" Name="AHBliteTop_utilization_placed.rpt"/>
  <File Type="PLACE-UTIL-PB" Name="AHBliteTop_utilization_placed.pb"/>
  <File Type="PLACE-CTRL" Name="AHBliteTop_control_sets_placed.rpt"/>
  <File Type="PLACE-SIMILARITY" Name="AHBliteTop_incremental_reuse_placed.rpt"/>
  <File Type="PLACE-PRE-SIMILARITY" Name="AHBliteTop_incremental_reuse_pre_placed.rpt"/>
  <File Type="POSTPLACE-PWROPT-DCP" Name="AHBliteTop_postplace_pwropt.dcp"/>
  <File Type="PHYSOPT-DCP" Name="AHBliteTop_physopt.dcp"/>
  <File Type="RDI-RDI" Name="AHBliteTop.vdi"/>
  <File Type="PHYSOPT-DRC" Name="AHBliteTop_drc_physopted.rpt"/>
  <File Type="ROUTE-DRC" Name="AHBliteTop_drc_routed.rpt"/>
  <File Type="ROUTE-DRC-PB" Name="AHBliteTop_drc_routed.pb"/>
  <File Type="ROUTE-PWR" Name="AHBliteTop_power_routed.rpt"/>
  <File Type="ROUTE-PWR-SUM" Name="AHBliteTop_power_summary_routed.pb"/>
  <File Type="ROUTE-STATUS" Name="AHBliteTop_route_status.rpt"/>
  <File Type="ROUTE-STATUS-PB" Name="AHBliteTop_route_status.pb"/>
  <File Type="ROUTE-TIMINGSUMMARY" Name="AHBliteTop_timing_summary_routed.rpt"/>
  <File Type="ROUTE-TIMING-PB" Name="AHBliteTop_timing_summary_routed.pb"/>
  <File Type="ROUTE-TIMING-RPX" Name="AHBliteTop_timing_summary_routed.rpx"/>
  <File Type="ROUTE-SIMILARITY" Name="AHBliteTop_incremental_reuse_routed.rpt"/>
  <File Type="ROUTE-CLK" Name="AHBliteTop_clock_utilization_routed.rpt"/>
  <File Type="POSTROUTE-PHYSOPT-DCP" Name="AHBliteTop_postroute_physopt.dcp"/>
  <File Type="POSTROUTE-PHYSOPT-TIMING" Name="AHBliteTop_timing_summary_postroute_physopted.rpt"/>
  <File Type="POSTROUTE-PHYSOPT-TIMING-PB" Name="AHBliteTop_timing_summary_postroute_physopted.pb"/>
  <File Type="POSTROUTE-PHYSOPT-TIMING-RPX" Name="AHBliteTop_timing_summary_postroute_physopted.rpx"/>
  <File Type="BG-BIT" Name="AHBliteTop.bit"/>
  <File Type="BG-BIN" Name="AHBliteTop.bin"/>
  <File Type="BITSTR-MSK" Name="AHBliteTop.msk"/>
  <File Type="BITSTR-RBT" Name="AHBliteTop.rbt"/>
  <File Type="BITSTR-NKY" Name="AHBliteTop.nky"/>
  <File Type="BITSTR-BMM" Name="AHBliteTop_bd.bmm"/>
  <File Type="BITSTR-MMI" Name="AHBliteTop.mmi"/>
  <File Type="BITSTR-SYSDEF" Name="AHBliteTop.sysdef"/>
  <File Type="BG-BGN" Name="AHBliteTop.bgn"/>
  <File Type="BG-DRC" Name="AHBliteTop.drc"/>
  <File Type="WBT-USG" Name="usage_statistics_webtalk.html"/>
  <FileSet Name="sources" Type="DesignSrcs" RelSrcDir="$PSRCDIR/sources_1">
    <Filter Type="Srcs"/>
    <File Path="$PPRDIR/Design/uart_RXonly.v">
      <FileInfo>
        <Attr Name="UsedIn" Val="synthesis"/>
        <Attr Name="UsedIn" Val="implementation"/>
        <Attr Name="UsedIn" Val="simulation"/>
      </FileInfo>
    </File>
    <File Path="$PPRDIR/Design/ram_loader.v">
      <FileInfo>
        <Attr Name="UsedIn" Val="synthesis"/>
        <Attr Name="UsedIn" Val="implementation"/>
        <Attr Name="UsedIn" Val="simulation"/>
      </FileInfo>
    </File>
    <File Path="$PPRDIR/Design/AHBrom.v">
      <FileInfo>
        <Attr Name="UsedIn" Val="synthesis"/>
        <Attr Name="UsedIn" Val="implementation"/>
        <Attr Name="UsedIn" Val="simulation"/>
      </FileInfo>
    </File>
    <File Path="$PPRDIR/Design/AHBram.v">
      <FileInfo>
        <Attr Name="UsedIn" Val="synthesis"/>
        <Attr Name="UsedIn" Val="implementation"/>
        <Attr Name="UsedIn" Val="simulation"/>
      </FileInfo>
    </File>
    <File Path="$PPRDIR/Design/status_ind.v">
      <FileInfo>
        <Attr Name="UsedIn" Val="synthesis"/>
        <Attr Name="UsedIn" Val="implementation"/>
        <Attr Name="UsedIn" Val="simulation"/>
      </FileInfo>
    </File>
    <File Path="$PPRDIR/Design/reset_gen.v">
      <FileInfo>
        <Attr Name="UsedIn" Val="synthesis"/>
        <Attr Name="UsedIn" Val="implementation"/>
        <Attr Name="UsedIn" Val="simulation"/>
      </FileInfo>
    </File>
    <File Path="$PPRDIR/Design/clock_gen.v">
      <FileInfo>
        <Attr Name="UsedIn" Val="synthesis"/>
        <Attr Name="UsedIn" Val="implementation"/>
        <Attr Name="UsedIn" Val="simulation"/>
      </FileInfo>
    </File>
    <File Path="$PPRDIR/Design/AHBMUX.v">
      <FileInfo>
        <Attr Name="UsedIn" Val="synthesis"/>
        <Attr Name="UsedIn" Val="implementation"/>
        <Attr Name="UsedIn" Val="simulation"/>
      </FileInfo>
    </File>
    <File Path="$PPRDIR/Design/AHBDCD.v">
      <FileInfo>
        <Attr Name="UsedIn" Val="synthesis"/>
        <Attr Name="UsedIn" Val="implementation"/>
        <Attr Name="UsedIn" Val="simulation"/>
      </FileInfo>
    </File>
    <File Path="$PPRDIR/Design/AHBliteTop.v">
      <FileInfo>
        <Attr Name="UsedIn" Val="synthesis"/>
        <Attr Name="UsedIn" Val="implementation"/>
        <Attr Name="UsedIn" Val="simulation"/>
      </FileInfo>
    </File>
    <File Path="$PPRDIR/Design/ROMcode4.coe">
      <FileInfo>
        <Attr Name="UsedIn" Val="synthesis"/>
      </FileInfo>
    </File>
    <File Path="$PPRDIR/Design/AHBuart.v">
      <FileInfo>
        <Attr Name="UsedIn" Val="synthesis"/>
        <Attr Name="UsedIn" Val="implementation"/>
        <Attr Name="UsedIn" Val="simulation"/>
      </FileInfo>
    </File>
    <File Path="$PPRDIR/Design/fifo.v">
      <FileInfo>
        <Attr Name="UsedIn" Val="synthesis"/>
        <Attr Name="UsedIn" Val="implementation"/>
        <Attr Name="UsedIn" Val="simulation"/>
      </FileInfo>
    </File>
    <File Path="$PPRDIR/Design/uart.v">
      <FileInfo>
        <Attr Name="UsedIn" Val="synthesis"/>
        <Attr Name="UsedIn" Val="implementation"/>
        <Attr Name="UsedIn" Val="simulation"/>
      </FileInfo>
    </File>
    <File Path="$PPRDIR/Design/AHBgpio.v">
      <FileInfo>
        <Attr Name="UsedIn" Val="synthesis"/>
        <Attr Name="UsedIn" Val="implementation"/>
        <Attr Name="UsedIn" Val="simulation"/>
      </FileInfo>
    </File>
    <File Path="$PPRDIR/Design/AHBdisp.v">
      <FileInfo>
        <Attr Name="UsedIn" Val="synthesis"/>
        <Attr Name="UsedIn" Val="implementation"/>
        <Attr Name="UsedIn" Val="simulation"/>
      </FileInfo>
    </File>
    <File Path="$PPRDIR/Design/AHBdummy.v">
      <FileInfo>
        <Attr Name="UsedIn" Val="synthesis"/>
        <Attr Name="UsedIn" Val="implementation"/>
        <Attr Name="UsedIn" Val="simulation"/>
      </FileInfo>
    </File>
    <Config>
      <Option Name="DesignMode" Val="RTL"/>
      <Option Name="TopModule" Val="AHBliteTop"/>
    </Config>
  </FileSet>
  <FileSet Name="constrs_in" Type="Constrs" RelSrcDir="$PSRCDIR/constrs_1">
    <Filter Type="Constrs"/>
    <File Path="$PPRDIR/Constraint/Nexys4_SoC.xdc">
      <FileInfo>
        <Attr Name="UsedIn" Val="synthesis"/>
        <Attr Name="UsedIn" Val="implementation"/>
      </FileInfo>
    </File>
    <Config>
      <Option Name="ConstrsType" Val="XDC"/>
    </Config>
  </FileSet>
  <Strategy Version="1" Minor="2">
    <StratHandle Name="Vivado Implementation Defaults" Flow="Vivado Implementation 2015"/>
    <Step Id="init_design"/>
    <Step Id="opt_design"/>
    <Step Id="power_opt_design"/>
    <Step Id="place_design"/>
    <Step Id="post_place_power_opt_design"/>
    <Step Id="phys_opt_design"/>
    <Step Id="route_design"/>
    <Step Id="post_route_phys_opt_design"/>
    <Step Id="write_bitstream"/>
  </Strategy>
  <BlockFileSet Type="BlockSrcs" Name="CORTEXM0DS"/>
  <BlockFileSet Type="BlockSrcs" Name="blk_mem_4Kword"/>
  <BlockFileSet Type="BlockSrcs" Name="blk_mem_8Kword"/>
</GenRun>
